Metadata-Version: 2.1
Name: topsis-101953010
Version: 1.1
Summary: A Python package to rank ML models/choices using topsis technique
Home-page: UNKNOWN
Author: Aditya Gupta
License: MIT
Platform: UNKNOWN
Classifier: License :: OSI Approved :: MIT License
Classifier: Programming Language :: Python :: 3
Classifier: Programming Language :: Python :: 3.7
